RepeatFS-0.10.0.data/scripts/repeatfs
repeatfs/__init__.py
repeatfs/api.py
repeatfs/cache_entry.py
repeatfs/client.py
repeatfs/configuration.py
repeatfs/core.py
repeatfs/descriptor_entry.py
repeatfs/file_entry.py
repeatfs/fuse.py
repeatfs/process_io.py
repeatfs/provenance.py
repeatfs/provenance/__init__.py
repeatfs/provenance/file_record.py
repeatfs/provenance/graph.py
repeatfs/provenance/graph_old.py
repeatfs/provenance/io_record.py
repeatfs/provenance/management.py
repeatfs/provenance/process_record.py
repeatfs/provenance/render_base.py
repeatfs/provenance/render_graphviz.html
repeatfs/provenance/render_graphviz.py
repeatfs/provenance/render_json.py
repeatfs/provenance/replication.py
RepeatFS-0.10.0.dist-info/LICENSE
RepeatFS-0.10.0.dist-info/METADATA
RepeatFS-0.10.0.dist-info/WHEEL
RepeatFS-0.10.0.dist-info/top_level.txt
RepeatFS-0.10.0.dist-info/RECORD
