Metadata-Version: 2.1
Name: RepeatFS
Version: 0.10.0
Summary: File system providing reproducibility through provenance and automation
Home-page: http://github.com/ToniWestbrook/repeatfs
Author: Anthony Westbrook
Author-email: anthony.westbrook@unh.edu
License: LICENSE
Platform: UNKNOWN
Classifier: Programming Language :: Python :: 3
Classifier: License :: OSI Approved :: GNU General Public License v3 (GPLv3)
Classifier: Operating System :: POSIX :: Linux
Requires-Dist: fusepy (>=3.0.1)
Requires-Dist: python-daemon (>=2.2.0)
Requires-Dist: pygraphviz (>=1.3.1)
